[{"org": {"type": "uri", "value": "http://www.wikidata.org/entity/Q59155583"}, "orgLabel": {"xml:lang": "en", "type": "literal", "value": "Bristol"}, "desc": {"xml:lang": "en", "type": "literal", "value": "Russian convenience store chain"}, "subsidiaries": {"type": "literal", "value": ""}, "members": {"type": "literal", "value": ""}, "industries": {"type": "literal", "value": "retail"}}, {"org": {"type": "uri", "value": "http://www.wikidata.org/entity/Q113067732"}, "orgLabel": {"xml:lang": "en", "type": "literal", "value": "Bristol"}, "desc": {"xml:lang": "en", "type": "literal", "value": "post office in Bristol, Quebec, Canada"}, "subsidiaries": {"type": "literal", "value": ""}, "members": {"type": "literal", "value": ""}, "industries": {"type": "literal", "value": ""}}, {"org": {"type": "uri", "value": "http://www.wikidata.org/entity/Q28469403"}, "orgLabel": {"xml:lang": "en", "type": "literal", "value": "Bristol"}, "desc": {"xml:lang": "en", "type": "literal", "value": "human settlement in Bristol, Quebec, Canada"}, "subsidiaries": {"type": "literal", "value": ""}, "members": {"type": "literal", "value": ""}, "industries": {"type": "literal", "value": ""}}, {"org": {"type": "uri", "value": "http://www.wikidata.org/entity/Q115260937"}, "orgLabel": {"xml:lang": "en", "type": "literal", "value": "Bristol"}, "desc": {"xml:lang": "en", "type": "literal", "value": "geographic township in Ontario, Canada"}, "subsidiaries": {"type": "literal", "value": ""}, "members": {"type": "literal", "value": ""}, "industries": {"type": "literal", "value": ""}}, {"org": {"type": "uri", "value": "http://www.wikidata.org/entity/Q2925666"}, "orgLabel": {"xml:lang": "en", "type": "literal", "value": "Bristol"}, "desc": {"xml:lang": "en", "type": "literal", "value": "municipality in Quebec, Canada"}, "subsidiaries": {"type": "literal", "value": ""}, "members": {"type": "literal", "value": ""}, "industries": {"type": "literal", "value": ""}}, {"org": {"type": "uri", "value": "http://www.wikidata.org/entity/Q568950"}, "orgLabel": {"xml:lang": "en", "type": "literal", "value": "Bristol"}, "desc": {"xml:lang": "en", "type": "literal", "value": "city in and the county seat of Liberty County, Florida, United States"}, "subsidiaries": {"type": "literal", "value": ""}, "members": {"type": "literal", "value": ""}, "industries": {"type": "literal", "value": ""}}, {"org": {"type": "uri", "value": "http://www.wikidata.org/entity/Q734001"}, "orgLabel": {"xml:lang": "en", "type": "literal", "value": "Bristol"}, "desc": {"xml:lang": "en", "type": "literal", "value": "town in Indiana"}, "subsidiaries": {"type": "literal", "value": ""}, "members": {"type": "literal", "value": ""}, "industries": {"type": "literal", "value": ""}}, {"org": {"type": "uri", "value": "http://www.wikidata.org/entity/Q755149"}, "orgLabel": {"xml:lang": "en", "type": "literal", "value": "Bristol"}, "desc": {"xml:lang": "en", "type": "literal", "value": "city in Hartford County, Connecticut, United States"}, "subsidiaries": {"type": "literal", "value": ""}, "members": {"type": "literal", "value": ""}, "industries": {"type": "literal", "value": ""}}, {"org": {"type": "uri", "value": "http://www.wikidata.org/entity/Q917802"}, "orgLabel": {"xml:lang": "en", "type": "literal", "value": "Bristol"}, "desc": {"xml:lang": "en", "type": "literal", "value": "town in New Hampshire, United States"}, "subsidiaries": {"type": "literal", "value": ""}, "members": {"type": "literal", "value": ""}, "industries": {"type": "literal", "value": ""}}, {"org": {"type": "uri", "value": "http://www.wikidata.org/entity/Q917821"}, "orgLabel": {"xml:lang": "en", "type": "literal", "value": "Bristol"}, "desc": {"xml:lang": "en", "type": "literal", "value": "city in Sullivan County, Tennessee, United States"}, "subsidiaries": {"type": "literal", "value": ""}, "members": {"type": "literal", "value": ""}, "industries": {"type": "literal", "value": ""}}, {"org": {"type": "uri", "value": "http://www.wikidata.org/entity/Q1861296"}, "orgLabel": {"xml:lang": "en", "type": "literal", "value": "Bristol"}, "desc": {"xml:lang": "en", "type": "literal", "value": "city in Day County, South Dakota, United States"}, "subsidiaries": {"type": "literal", "value": ""}, "members": {"type": "literal", "value": ""}, "industries": {"type": "literal", "value": ""}}, {"org": {"type": "uri", "value": "http://www.wikidata.org/entity/Q3708405"}, "orgLabel": {"xml:lang": "en", "type": "literal", "value": "Bristol"}, "desc": {"xml:lang": "en", "type": "literal", "value": "human settlement in Ontario County, New York, United States of America"}, "subsidiaries": {"type": "literal", "value": ""}, "members": {"type": "literal", "value": ""}, "industries": {"type": "literal", "value": ""}}, {"org": {"type": "uri", "value": "http://www.wikidata.org/entity/Q3709271"}, "orgLabel": {"xml:lang": "en", "type": "literal", "value": "Bristol"}, "desc": {"xml:lang": "en", "type": "literal", "value": "village in Kenosha County, Wisconsin"}, "subsidiaries": {"type": "literal", "value": ""}, "members": {"type": "literal", "value": ""}, "industries": {"type": "literal", "value": ""}}, {"org": {"type": "uri", "value": "http://www.wikidata.org/entity/Q503366"}, "orgLabel": {"xml:lang": "en", "type": "literal", "value": "Bristol"}, "desc": {"xml:lang": "en", "type": "literal", "value": "independent city in Virginia, United States"}, "subsidiaries": {"type": "literal", "value": ""}, "members": {"type": "literal", "value": ""}, "industries": {"type": "literal", "value": ""}}, {"org": {"type": "uri", "value": "http://www.wikidata.org/entity/Q1132588"}, "orgLabel": {"xml:lang": "en", "type": "literal", "value": "Bristol"}, "desc": {"xml:lang": "en", "type": "literal", "value": "borough in Bucks County, Pennsylvania, United States"}, "subsidiaries": {"type": "literal", "value": ""}, "members": {"type": "literal", "value": ""}, "industries": {"type": "literal", "value": ""}}, {"org": {"type": "uri", "value": "http://www.wikidata.org/entity/Q917809"}, "orgLabel": {"xml:lang": "en", "type": "literal", "value": "Bristol"}, "desc": {"xml:lang": "en", "type": "literal", "value": "town in Rhode Island, United States"}, "subsidiaries": {"type": "literal", "value": ""}, "members": {"type": "literal", "value": ""}, "industries": {"type": "literal", "value": ""}}, {"org": {"type": "uri", "value": "http://www.wikidata.org/entity/Q1871330"}, "orgLabel": {"xml:lang": "en", "type": "literal", "value": "Bristol"}, "desc": {"xml:lang": "en", "type": "literal", "value": "town in the United States"}, "subsidiaries": {"type": "literal", "value": ""}, "members": {"type": "literal", "value": ""}, "industries": {"type": "literal", "value": ""}}, {"org": {"type": "uri", "value": "http://www.wikidata.org/entity/Q2740437"}, "orgLabel": {"xml:lang": "en", "type": "literal", "value": "Bristol"}, "desc": {"xml:lang": "en", "type": "literal", "value": "town in Maine, United States"}, "subsidiaries": {"type": "literal", "value": ""}, "members": {"type": "literal", "value": ""}, "industries": {"type": "literal", "value": ""}}, {"org": {"type": "uri", "value": "http://www.wikidata.org/entity/Q23154"}, "orgLabel": {"xml:lang": "en", "type": "literal", "value": "Bristol"}, "desc": {"xml:lang": "en", "type": "literal", "value": "city in South West England, United Kingdom"}, "subsidiaries": {"type": "literal", "value": ""}, "members": {"type": "literal", "value": "Creative Cities Network"}, "industries": {"type": "literal", "value": ""}}]