[{"org": {"type": "uri", "value": "http://www.wikidata.org/entity/Q9584"}, "orgLabel": {"xml:lang": "en", "type": "literal", "value": "Honda"}, "desc": {"xml:lang": "en", "type": "literal", "value": "manufacturer of automobiles, motorcycles, and power equipment"}, "subsidiaries": {"type": "literal", "value": "Honda Racing Corporation;Honda Aircraft Company;Honda Canada;Honda Manufacturing of Alabama;Honda of the UK Manufacturing;GE Honda Aero Engines;American Honda Motor Company;Dongfeng Honda;Everus;HMSI;Honda Atlas Cars Pakistan;Honda Express;Honda Taiwan;Honda Mobilityland;Honda R&D;Honda Cars India;Honda Aero;Astra Honda Motor;Montesa Honda;Honda Prospect Motor;Honda Australia;Honda Auto Body;Sony Honda Mobility"}, "members": {"type": "literal", "value": "Linux Foundation;Open Automotive Alliance"}, "industries": {"type": "literal", "value": "manufacturing;automotive industry"}}, {"org": {"type": "uri", "value": "http://www.wikidata.org/entity/Q11520621"}, "orgLabel": {"xml:lang": "en", "type": "literal", "value": "Honda"}, "desc": {"xml:lang": "en", "type": "literal", "value": "dissolved municipality in Kitakanbara district, Niigata prefecture, Japan"}, "subsidiaries": {"type": "literal", "value": ""}, "members": {"type": "literal", "value": ""}, "industries": {"type": "literal", "value": ""}}, {"org": {"type": "uri", "value": "http://www.wikidata.org/entity/Q11631434"}, "orgLabel": {"xml:lang": "en", "type": "literal", "value": "Honda"}, "desc": {"xml:lang": "en", "type": "literal", "value": "dissolved municipality in Ibo district, Hy\u014dgo prefecture, Japan"}, "subsidiaries": {"type": "literal", "value": ""}, "members": {"type": "literal", "value": ""}, "industries": {"type": "literal", "value": ""}}, {"org": {"type": "uri", "value": "http://www.wikidata.org/entity/Q11631435"}, "orgLabel": {"xml:lang": "en", "type": "literal", "value": "Honda"}, "desc": {"xml:lang": "en", "type": "literal", "value": "dissolved municipality in Chiba district, Chiba prefecture, Japan"}, "subsidiaries": {"type": "literal", "value": ""}, "members": {"type": "literal", "value": ""}, "industries": {"type": "literal", "value": ""}}, {"org": {"type": "uri", "value": "http://www.wikidata.org/entity/Q11631436"}, "orgLabel": {"xml:lang": "en", "type": "literal", "value": "Honda"}, "desc": {"xml:lang": "en", "type": "literal", "value": "dissolved municipality in Kuji district, Ibaraki prefecture, Japan"}, "subsidiaries": {"type": "literal", "value": ""}, "members": {"type": "literal", "value": ""}, "industries": {"type": "literal", "value": ""}}, {"org": {"type": "uri", "value": "http://www.wikidata.org/entity/Q17176313"}, "orgLabel": {"xml:lang": "en", "type": "literal", "value": "Honda"}, "desc": {"xml:lang": "en", "type": "literal", "value": "dissolved municipality in Ikoma district, Nara prefecture, Japan"}, "subsidiaries": {"type": "literal", "value": ""}, "members": {"type": "literal", "value": ""}, "industries": {"type": "literal", "value": ""}}, {"org": {"type": "uri", "value": "http://www.wikidata.org/entity/Q932513"}, "orgLabel": {"xml:lang": "en", "type": "literal", "value": "Honda"}, "desc": {"xml:lang": "en", "type": "literal", "value": "Colombian municipality of the department of Tolima"}, "subsidiaries": {"type": "literal", "value": ""}, "members": {"type": "literal", "value": ""}, "industries": {"type": "literal", "value": ""}}]